<?xml version="1.0" encoding="UTF-8" ?>
<!DOCTYPE mapper PUBLIC "-//mybatis.org//DTD Mapper 3.0//EN" "http://mybatis.org/dtd/mybatis-3-mapper.dtd">
<mapper namespace="com.example.board.mapper.BoardMapper">

    <insert id="insertBoard" parameterType="com.example.board.api.v1.board.domain.Board">
        <selectKey keyProperty="boardId" resultType="java.lang.Long" order="AFTER">
            SELECT LAST_INSERT_ID()
        </selectKey>
        INSERT INTO BOARD(
        BOARD_ID,
        WRITER,
        TITLE,
        CONTENT,
        CREATED_DATE,
        MODIFIED_DATE
        ) VALUES (
        #{boardId},
        #{writer},
        #{title},
        #{content},
        SYSDATE(),
        #{modifiedDate}
        )
    </insert>

    <update id="updateBoard" parameterType="com.example.board.api.v1.board.domain.Board">
        UPDATE BOARD
        <set>
            <if test="title != null and !title.equals('')">TITLE = #{title},</if>
            <if test="content != null and !content.equals('')">CONTENT = #{content},</if>
            MODIFIED_DATE = SYSDATE()
        </set>
        WHERE BOARD_ID = #{boardId}
    </update>

    <select id="selectBoardById" parameterType="java.lang.Long"
            resultType="com.example.board.api.v1.board.domain.Board">
        SELECT BOARD_ID,
               TITLE,
               CONTENT,
               WRITER,
               DATE_FORMAT(CREATED_DATE, '%Y-%m-%d %H:%i:%s')  AS CREATED_DATE,
               DATE_FORMAT(MODIFIED_DATE, '%Y-%m-%d %H:%i:%s') AS MODIFIED_DATE
        FROM BOARD
        WHERE BOARD_ID = #{boardId}
    </select>

    <select id="selectAllBoards"
            resultType="com.example.board.api.v1.board.domain.Board">
        SELECT BOARD_ID,
               TITLE,
               CONTENT,
               WRITER,
               DATE_FORMAT(CREATED_DATE, '%Y-%m-%d %H:%i:%s')  AS CREATED_DATE,
               DATE_FORMAT(MODIFIED_DATE, '%Y-%m-%d %H:%i:%s') AS MODIFIED_DATE
        FROM BOARD
    </select>

    <delete id="deleteBoardById" parameterType="java.lang.Long">
        DELETE
        FROM BOARD
        WHERE BOARD_ID = #{boardId}
    </delete>

    <delete id="deleteAllBoards">
        DELETE
        FROM BOARD
    </delete>

</mapper>
